vstock_data/__init__.py
vstock_data/data_loader.py
vstock_data-1.0.1.dist-info/licenses/LICENSE
vstock_data-1.0.1.dist-info/METADATA
vstock_data-1.0.1.dist-info/WHEEL
vstock_data-1.0.1.dist-info/top_level.txt
vstock_data-1.0.1.dist-info/RECORD
