Metadata-Version: 2.4
Name: vstock-data
Version: 1.0.1
Summary: Thư viện Python tải dữ liệu chứng khoán Việt Nam từ nhiều nguồn khác nhau.
Author-email: Hunter Do <phongvu2010@gmail.com>
License: MIT License
Project-URL: Homepage, https://github.com/phongvu2010/vStock-Data
Project-URL: Bug Tracker, https://github.com/phongvu2010/vStock-Data/issues
Classifier: Programming Language :: Python :: 3
Classifier: License :: OSI Approved :: MIT License
Classifier: Operating System :: OS Independent
Classifier: Topic :: Office/Business :: Financial :: Investment
Requires-Python: >=3.10
License-File: LICENSE
Requires-Dist: pandas
Requires-Dist: yfinance
Requires-Dist: google-cloud-bigquery
Dynamic: license-file
